cloud_passport_cli/__init__.py
cloud_passport_cli/__main__.py
cloud_passport_cli/collector.py
cloud_passport_cli/connect.py
cloud_passport_cli/discovery.py
cloud_passport_cli/main.py
cloud_passport_cli/scrapers.py
cloud_passport_cli/templating.py
cloud_passport_cli/utility.py
qubership_cloud_passport_cli-2.3.5.dist-info/LICENSE
qubership_cloud_passport_cli-2.3.5.dist-info/METADATA
qubership_cloud_passport_cli-2.3.5.dist-info/WHEEL
qubership_cloud_passport_cli-2.3.5.dist-info/entry_points.txt
qubership_cloud_passport_cli-2.3.5.dist-info/RECORD
